<annotation>
	<folder>gucci</folder>
	<filename>Gucci50.jpg</filename>
	<path>/home/zi/Desktop/jpg/gucci/Gucci50.jpg</path>
	<source>
		<database>Unknown</database>
	</source>
	<size>
		<width>640</width>
		<height>425</height>
		<depth>3</depth>
	</size>
	<segmented>0</segmented>
	<object>
		<name>Gucci</name>
		<pose>Unspecified</pose>
		<truncated>0</truncated>
		<difficult>0</difficult>
		<bndbox>
			<xmin>16</xmin>
			<ymin>185</ymin>
			<xmax>629</xmax>
			<ymax>290</ymax>
		</bndbox>
	</object>
</annotation>
