<annotation>
	<folder>mk</folder>
	<filename>MK67.jpg</filename>
	<path>/home/zi/Desktop/jpg/mk/MK67.jpg</path>
	<source>
		<database>Unknown</database>
	</source>
	<size>
		<width>370</width>
		<height>401</height>
		<depth>3</depth>
	</size>
	<segmented>0</segmented>
	<object>
		<name>Michael Kors</name>
		<pose>Unspecified</pose>
		<truncated>0</truncated>
		<difficult>0</difficult>
		<bndbox>
			<xmin>135</xmin>
			<ymin>266</ymin>
			<xmax>174</xmax>
			<ymax>295</ymax>
		</bndbox>
	</object>
</annotation>
